.long-description.html
README.rst
setup.py
src/collective/__init__.py
src/collective.cart.shopping.egg-info/PKG-INFO
src/collective.cart.shopping.egg-info/SOURCES.txt
src/collective.cart.shopping.egg-info/dependency_links.txt
src/collective.cart.shopping.egg-info/entry_points.txt
src/collective.cart.shopping.egg-info/namespace_packages.txt
src/collective.cart.shopping.egg-info/not-zip-safe
src/collective.cart.shopping.egg-info/requires.txt
src/collective.cart.shopping.egg-info/top_level.txt
src/collective/cart/__init__.py
src/collective/cart/shopping/__init__.py
src/collective/cart/shopping/config.py
src/collective/cart/shopping/configure.zcml
src/collective/cart/shopping/content.py
src/collective/cart/shopping/event.py
src/collective/cart/shopping/interfaces.py
src/collective/cart/shopping/schema.py
src/collective/cart/shopping/subscriber.py
src/collective/cart/shopping/upgrades.py
src/collective/cart/shopping/upgrades.zcml
src/collective/cart/shopping/vocabulary.py
src/collective/cart/shopping/Extensions/Install.py
src/collective/cart/shopping/Extensions/__init__.py
src/collective/cart/shopping/adapter/__init__.py
src/collective/cart/shopping/adapter/article.py
src/collective/cart/shopping/adapter/configure.zcml
src/collective/cart/shopping/adapter/content_listing_object.py
src/collective/cart/shopping/adapter/interface.py
src/collective/cart/shopping/adapter/order.py
src/collective/cart/shopping/adapter/order_article.py
src/collective/cart/shopping/adapter/validator.py
src/collective/cart/shopping/browser/__init__.py
src/collective/cart/shopping/browser/ajax.py
src/collective/cart/shopping/browser/base.py
src/collective/cart/shopping/browser/configure.zcml
src/collective/cart/shopping/browser/interfaces.py
src/collective/cart/shopping/browser/miscellaneous.py
src/collective/cart/shopping/browser/view.py
src/collective/cart/shopping/browser/viewlet.py
src/collective/cart/shopping/browser/viewletmanager.py
src/collective/cart/shopping/browser/static/article-container.png
src/collective/cart/shopping/browser/static/customer-info.png
src/collective/cart/shopping/browser/static/shop.png
src/collective/cart/shopping/browser/static/transparent.gif
src/collective/cart/shopping/browser/static/css/style.css
src/collective/cart/shopping/browser/static/javascript/check-out-buttons.js
src/collective/cart/shopping/browser/static/javascript/select-subarticle.js
