Metadata-Version: 1.1
Name: collective.cart.shopping
Version: 0.12
Summary: Shopping site suit for Plone.
Home-page: https://github.com/collective/collective.cart.shopping/
Author: Taito Horiuchi
Author-email: taito.horiuchi@gmail.com
License: BSD
Platform: UNKNOWN
Classifier: Framework :: Plone
Classifier: Framework :: Plone :: 4.3
Classifier: License :: OSI Approved :: BSD License
Classifier: Programming Language :: Python
Classifier: Programming Language :: Python :: 2.7
